quest/__init__.py
quest/core.py
quest/core_depr.py
quest/decoding_depr.py
quest/index.py
quest/jacobi.py
quest/proposal.py
quest/qalign.py
quest/model/__init__.py
quest/model/base.py
quest/model/hf.py
quest/model/hf2.py
quest/model/jacobi.py
quest/model/remote.py
quest/model/simm.py
quest/model/test.py
quest/model/vllm.py
quest/reward/__init__.py
quest/reward/base.py
quest/reward/model.py
quest/reward/mt.py
quest/reward/remote.py
quest/utils/__init__.py
quest/utils/data.py
quest/utils/http.py
quest/utils/list.py
quest/utils/logger.py
quest/utils/math.py
tests/__init__.py
tests/test_decoding.py
tests/test_qe.py
tests/test_questqe.py
tests/test_rewardmodel.py
tests/test_vllm.py
quest_decoding-1.0.16.dist-info/LICENSE
quest_decoding-1.0.16.dist-info/METADATA
quest_decoding-1.0.16.dist-info/WHEEL
quest_decoding-1.0.16.dist-info/top_level.txt
quest_decoding-1.0.16.dist-info/RECORD
