Metadata-Version: 2.1
Name: quest-decoding
Version: 1.0.16
Summary: A package for sampling from intractable distributions with LLMs.
Home-page: https://github.com/deep-spin/quest-decoding
Author: Goncalo Faria, Sweta Agrawal.
Author-email: goncalofaria.research@gmail.com, swetaagrawal20@gmail.com
Classifier: Programming Language :: Python :: 3
Classifier: License :: OSI Approved :: MIT License
Classifier: Operating System :: OS Independent
Requires-Python: >=3.8.0
License-File: LICENSE
Requires-Dist: langchain >=0.0.352
Requires-Dist: numpy >=1.24.4
Requires-Dist: transformers
Requires-Dist: vllm >=0.2.6
Requires-Dist: scipy >=1.9.3
Requires-Dist: unbabel-comet
Requires-Dist: torchmetrics ==0.10.3
